agent_config/__init__.py
agent_config/cli.py
agent_config/defaults.py
agent_config/env.py
agent_config/formats.py
agent_config/load.py
agent_config/validate.py
agent_config-0.1.0.dist-info/METADATA
agent_config-0.1.0.dist-info/WHEEL
agent_config-0.1.0.dist-info/entry_points.txt
agent_config-0.1.0.dist-info/top_level.txt
agent_config-0.1.0.dist-info/RECORD
