Metadata-Version: 2.4
Name: agent-config
Version: 0.1.0
Summary: Agent configuration loader and normalizer for AI/LLM applications
Author-email: Andrew Gao <andrew@example.com>
Project-URL: Homepage, https://github.com/andrewgcodes/merciful-delicate-samovar
Project-URL: Repository, https://github.com/andrewgcodes/merciful-delicate-samovar
Project-URL: Issues, https://github.com/andrewgcodes/merciful-delicate-samovar/issues
Keywords: agent,config,configuration,llm,ai,yaml,json,environment
Classifier: Development Status :: 4 - Beta
Classifier: Intended Audience :: Developers
Classifier: Operating System :: OS Independent
Classifier: Programming Language :: Python :: 3
Classifier: Programming Language :: Python :: 3.9
Classifier: Programming Language :: Python :: 3.10
Classifier: Programming Language :: Python :: 3.11
Classifier: Programming Language :: Python :: 3.12
Classifier: Topic :: Software Development :: Libraries :: Python Modules
Classifier: Topic :: Utilities
Requires-Python: >=3.9
Requires-Dist: PyYAML>=6.0
Provides-Extra: toml
Requires-Dist: tomli>=2.0; python_version < "3.11" and extra == "toml"
Provides-Extra: dev
Requires-Dist: pytest>=7.0; extra == "dev"
Requires-Dist: pytest-cov>=4.0; extra == "dev"
Requires-Dist: build>=1.0; extra == "dev"
Requires-Dist: twine>=4.0; extra == "dev"
